{
  "id": "376",
  "slug": "in-lausanne-bus-tour-to-interlaken-with-harder-kulm",
  "name": "In Lausanne: Bus tour to Interlaken with Harder Kulm",
  "description": "Discover In Lausanne: Bus tour to Interlaken with Harder Kulm in Switzerland.",
  "longDescription": "Discover In Lausanne: Bus tour to Interlaken with Harder Kulm in Switzerland.",
  "category": "outdoor",
  "subcategory": "Day trips",
  "location": {
    "region": "Lake Geneva region",
    "canton": "",
    "city": "Switzerland",
    "coordinates": {
      "lat": 46.8182,
      "lng": 8.2275
    }
  },
  "seasons": [
    "summer"
  ],
  "indoor": false,
  "providers": [
    {
      "name": "SwissActivities",
      "pricing": {
        "child": 0,
        "student": 0,
        "adult": 0,
        "senior": 0
      },
      "bookingUrl": "https://www.swissactivities.com/en-ch/day-trips/in-lausanne-bus-tour-to-interlaken-with-harder-kulm/?ref=odbhodn",
      "rating": 4.4,
      "description": "Switzerland's largest activities marketplace — book securely online"
    }
  ],
  "currency": "CHF",
  "duration": "Varies",
  "imageUrl": "https://images.unsplash.com/photo-1531973576160-7125cd663d86?w=800&h=500&fit=crop",
  "gallery": [],
  "highlights": [],
  "tags": [
    "lake",
    "interlaken",
    "lausanne"
  ],
  "featured": false
}
