{
  "id": "1297",
  "slug": "marzilibahn-ticket-bern",
  "name": " Marzilibahn ticket in Bern",
  "description": "Discover  Marzilibahn ticket in Bern in Switzerland.",
  "longDescription": "Discover  Marzilibahn ticket in Bern in Switzerland.",
  "category": "outdoor",
  "subcategory": "Train ticket",
  "location": {
    "region": "Bern Region",
    "canton": "",
    "city": "Switzerland",
    "coordinates": {
      "lat": 46.8182,
      "lng": 8.2275
    }
  },
  "seasons": [
    "summer"
  ],
  "indoor": false,
  "providers": [
    {
      "name": "SwissActivities",
      "pricing": {
        "child": 0,
        "student": 0,
        "adult": 0,
        "senior": 0
      },
      "bookingUrl": "https://www.swissactivities.com/en-ch/train-ride/marzilibahn-ticket-bern/?ref=odbhodn",
      "rating": 4.4,
      "description": "Switzerland's largest activities marketplace — book securely online"
    }
  ],
  "currency": "CHF",
  "duration": "Varies",
  "imageUrl": "https://images.unsplash.com/photo-1531973576160-7125cd663d86?w=800&h=500&fit=crop",
  "gallery": [],
  "highlights": [],
  "tags": [
    "bern"
  ],
  "featured": false
}
