{
  "slug": "switzerland-vs-austria-skiing-price-comparison",
  "title": "Switzerland vs Austria Skiing: Full Price Comparison 2026",
  "excerpt": "Is skiing in Austria really cheaper than Switzerland? We compare lift passes, accommodation, food, and equipment rental costs side by side.",
  "date": "2026-01-18",
  "author": "Tom Lindqvist",
  "tags": [
    "skiing",
    "budget",
    "comparison",
    "austria"
  ],
  "content": "The age-old Alpine debate: should you ski in Switzerland or Austria? While Austria has a reputation for being cheaper, the gap isn't always as wide as you'd think. Here's a **detailed price comparison** for the 2025/2026 season.\n\n## Lift Pass Prices\n\n| Category | Switzerland (avg) | Austria (avg) |\n|---|---|---|\n| Adult day pass | CHF 65-75 | EUR 55-65 (~CHF 53-63) |\n| Youth day pass | CHF 50-60 | EUR 40-50 (~CHF 39-48) |\n| 6-day pass | CHF 320-380 | EUR 280-330 (~CHF 270-320) |\n\n**Verdict:** Austria is roughly **15-20% cheaper** on lift passes, though budget Swiss resorts can match Austrian mid-range prices.\n\n## Accommodation\n\n- **Swiss budget hotel:** CHF 120-180/night for a double room\n- **Austrian budget hotel:** EUR 80-130/night (~CHF 77-125)\n- **Swiss apartment rental:** CHF 100-200/night (4 persons)\n- **Austrian apartment rental:** EUR 70-150/night (~CHF 68-145)\n\n**Verdict:** Austria wins by **25-35%** on accommodation, especially in the Tirol region where options are plentiful.\n\n## Food & Drink\n\n- **Mountain restaurant lunch (Switzerland):** CHF 22-30 for a main course\n- **Mountain restaurant lunch (Austria):** EUR 12-18 (~CHF 12-17) for a main course\n- **Beer on the slopes (Switzerland):** CHF 7-9\n- **Beer on the slopes (Austria):** EUR 4-5 (~CHF 4-5)\n- **Supermarket groceries (Switzerland):** roughly 40-60% more expensive\n\n**Verdict:** This is where the **biggest gap** exists. On-mountain dining in Austria is roughly **40-50% cheaper**. Self-catering in Austria saves even more.\n\n## Equipment Rental\n\n- **Ski + boots + poles (Switzerland):** CHF 45-65/day\n- **Ski + boots + poles (Austria):** EUR 30-45/day (~CHF 29-43)\n\n**Verdict:** Austria is **20-30% cheaper** on rentals.\n\n## Total Cost Comparison: 6-Day Ski Holiday for Two Adults\n\n| Expense | Switzerland | Austria |\n|---|---|---|\n| 6-day lift pass x2 | CHF 700 | CHF 560 |\n| 6 nights hotel | CHF 900 | CHF 600 |\n| Food & drink | CHF 600 | CHF 350 |\n| Equipment rental | CHF 500 | CHF 350 |\n| **Total** | **CHF 2,700** | **CHF 1,860** |\n\nThat's roughly a **CHF 840 difference** — about 31% cheaper in Austria.\n\n## But Wait — Where Switzerland Wins\n\n- **Snow reliability** — Swiss resorts are generally higher altitude (more glacier skiing)\n- **Scenery** — The iconic Matterhorn, Eiger, and Jungfrau are unmatched\n- **Less crowded** — Austrian resorts, especially in Tirol, can feel packed during peak season\n- **Longer season** — Several Swiss resorts operate well into April or even May\n- **Infrastructure quality** — Swiss lifts and grooming are often a notch above\n\n## The Bottom Line\n\nAustria is **undeniably cheaper** for a ski holiday, especially on food and accommodation. But Switzerland offers better snow reliability, more dramatic scenery, and generally fewer crowds. If budget is your primary concern, Austria wins. If you're after a once-in-a-lifetime Alpine experience, Switzerland delivers.\n\n**Pro tip:** You can split the difference by staying in a Swiss town near the Austrian border (like Buchs or St. Margrethen) and skiing in Austrian Vorarlberg. You get Swiss rail convenience with Austrian prices on the mountain."
}
